{
  "type": "image",
  "name": "img-event-workshop",
  "resolution": "instagram-post",
  "outputFormat": "png",
  "backgroundColor": "#0C0F0A",
  "variables": {
    "eyebrow": "HANDS-ON WORKSHOP",
    "titleA": "Build & Ship an",
    "titleB": "AI Agent",
    "titleC": "in a Day",
    "chip1": "Prompt design",
    "chip2": "Tool calling",
    "chip3": "Eval loops",
    "chip4": "Deploy to prod",
    "seatsLabel": "SEATS LEFT",
    "seatsValue": "12",
    "dateLabel": "Sat · Apr 25 · 10AM–4PM",
    "ink": "#0C0F0A",
    "accent": "#C6F24E",
    "bgImage": "https://images.pexels.com/photos/8219392/pexels-photo-8219392.jpeg?auto=compress&cs=tinysrgb&w=1600"
  },
  "visuals": [
    {
      "type": "IMAGE",
      "src": "{{bgImage}}",
      "width": 1080,
      "height": 1080,
      "position": "center-center",
      "resize": "cover",
      "track": 0
    },
    {
      "type": "SVG",
      "width": 1080,
      "height": 1080,
      "position": "center-center",
      "track": 1,
      "svg": "<svg width='1080' height='1080' viewBox='0 0 1080 1080' xmlns='http://www.w3.org/2000/svg'><defs><linearGradient id='sy' x1='0' y1='1' x2='0' y2='0'><stop offset='0' stop-color='{{ink}}' stop-opacity='0.97'/><stop offset='0.48' stop-color='{{ink}}' stop-opacity='0.68'/><stop offset='1' stop-color='{{ink}}' stop-opacity='0.28'/></linearGradient><linearGradient id='sx' x1='0' y1='0' x2='1' y2='0'><stop offset='0' stop-color='{{ink}}' stop-opacity='0.7'/><stop offset='0.6' stop-color='{{ink}}' stop-opacity='0'/></linearGradient></defs><rect width='1080' height='1080' fill='url(#sy)'/><rect width='1080' height='1080' fill='url(#sx)'/></svg>"
    },
    {
      "type": "SVG",
      "x": 80,
      "y": 92,
      "width": 360,
      "height": 48,
      "anchor": "top-left",
      "track": 4,
      "svg": "<svg width='360' height='48' viewBox='0 0 360 48' xmlns='http://www.w3.org/2000/svg'><rect x='1' y='1' width='330' height='46' rx='23' fill='{{accent}}'/><text x='166' y='31' font-family='Space Grotesk, Arial' font-size='18' font-weight='700' letter-spacing='3.5' fill='{{ink}}' text-anchor='middle'>{{eyebrow}}</text></svg>"
    },
    {
      "type": "SVG",
      "x": 820,
      "y": 84,
      "width": 180,
      "height": 180,
      "anchor": "top-left",
      "track": 4,
      "svg": "<svg width='180' height='180' viewBox='0 0 180 180' xmlns='http://www.w3.org/2000/svg'><circle cx='90' cy='90' r='88' fill='{{ink}}' fill-opacity='0.55' stroke='{{accent}}' stroke-width='2'/><text x='90' y='96' font-family='Space Grotesk, Arial' font-size='68' font-weight='700' fill='{{accent}}' text-anchor='middle'>{{seatsValue}}</text><text x='90' y='134' font-family='Space Grotesk, Arial' font-size='15' font-weight='600' letter-spacing='3' fill='#E7EFD6' text-anchor='middle'>{{seatsLabel}}</text></svg>"
    },
    {
      "type": "TEXT",
      "x": 78,
      "y": 348,
      "width": 760,
      "anchor": "top-left",
      "track": 5,
      "style": { "fontFamily": "Space Grotesk" },
      "html": "<div style='font-size:96px; font-weight:700; line-height:0.96; letter-spacing:-0.03em; color:#F5FBEA;'>{{titleA}} <span style='color:{{accent}};'>{{titleB}}</span> {{titleC}}</div>"
    },
    {
      "type": "TEXT",
      "x": 80,
      "y": 656,
      "width": 700,
      "anchor": "top-left",
      "track": 5,
      "text": "{{dateLabel}}",
      "style": {
        "fontFamily": "Inter",
        "fontSize": "26px",
        "fontWeight": "600",
        "letterSpacing": "0.02em",
        "color": "#C7D0B7"
      }
    },
    {
      "type": "SVG",
      "x": 80,
      "y": 748,
      "width": 920,
      "height": 60,
      "anchor": "top-left",
      "track": 5,
      "svg": "<svg width='920' height='60' viewBox='0 0 920 60' xmlns='http://www.w3.org/2000/svg'><rect x='1' y='1' width='200' height='58' rx='29' fill='#FFFFFF' fill-opacity='0.07' stroke='{{accent}}' stroke-opacity='0.45' stroke-width='1.2'/><circle cx='34' cy='30' r='5' fill='{{accent}}'/><text x='52' y='38' font-family='Inter, Arial' font-size='21' font-weight='600' fill='#EAF2DB'>{{chip1}}</text><rect x='216' y='1' width='190' height='58' rx='29' fill='#FFFFFF' fill-opacity='0.07' stroke='{{accent}}' stroke-opacity='0.45' stroke-width='1.2'/><circle cx='250' cy='30' r='5' fill='{{accent}}'/><text x='268' y='38' font-family='Inter, Arial' font-size='21' font-weight='600' fill='#EAF2DB'>{{chip2}}</text><rect x='421' y='1' width='170' height='58' rx='29' fill='#FFFFFF' fill-opacity='0.07' stroke='{{accent}}' stroke-opacity='0.45' stroke-width='1.2'/><circle cx='455' cy='30' r='5' fill='{{accent}}'/><text x='473' y='38' font-family='Inter, Arial' font-size='21' font-weight='600' fill='#EAF2DB'>{{chip3}}</text><rect x='606' y='1' width='210' height='58' rx='29' fill='#FFFFFF' fill-opacity='0.07' stroke='{{accent}}' stroke-opacity='0.45' stroke-width='1.2'/><circle cx='640' cy='30' r='5' fill='{{accent}}'/><text x='658' y='38' font-family='Inter, Arial' font-size='21' font-weight='600' fill='#EAF2DB'>{{chip4}}</text></svg>"
    },
    {
      "type": "SVG",
      "x": 80,
      "y": 892,
      "width": 320,
      "height": 56,
      "anchor": "top-left",
      "track": 6,
      "svg": "<svg width='320' height='56' viewBox='0 0 320 56' xmlns='http://www.w3.org/2000/svg'><circle cx='16' cy='28' r='7' fill='{{accent}}'/><text x='36' y='36' font-family='Space Grotesk, Arial' font-size='23' font-weight='600' letter-spacing='0.5' fill='#F5FBEA'>zvid.io/workshop</text></svg>"
    }
  ]
}
